osuhw/__init__.py
osuhw/hw.py
osuhw-0.0.1.dist-info/LICENSE
osuhw-0.0.1.dist-info/METADATA
osuhw-0.0.1.dist-info/WHEEL
osuhw-0.0.1.dist-info/top_level.txt
osuhw-0.0.1.dist-info/RECORD
