Metadata-Version: 2.1
Name: osuhw
Version: 0.0.1
Summary: For getting your engr 103 hw done quickly
Home-page: https://github.com/Hopalonger/10EngineeringProblems
Author: Ryan Hopkins
Author-email: hopkinsr@oregonstate.edu
License: UNKNOWN
Platform: UNKNOWN
Classifier: Programming Language :: Python :: 3
Classifier: License :: OSI Approved :: MIT License
Classifier: Operating System :: OS Independent
Requires-Python: >=3.7
License-File: LICENSE
